vkudak_exchange_rates/__init__.py
vkudak_exchange_rates/exchange_rates.py
vkudak_exchange_rates-0.0.6.dist-info/LICENSE
vkudak_exchange_rates-0.0.6.dist-info/METADATA
vkudak_exchange_rates-0.0.6.dist-info/WHEEL
vkudak_exchange_rates-0.0.6.dist-info/top_level.txt
vkudak_exchange_rates-0.0.6.dist-info/RECORD
