Metadata-Version: 2.1
Name: vkudak-exchange-rates
Version: 0.0.6
Summary: A small library for getting information on some currency exchange rates into UAH, on the selected date
Author: Viktor Kudak
Author-email: vkudak@gmail.com
License: MIT
Project-URL: Source, https://gtlb.jetsoftpro.com/vkudak/vkudak-exchange-rates
Keywords: python,exchange rate
Platform: UNKNOWN
Classifier: Intended Audience :: Education
Classifier: Programming Language :: Python :: 3
Classifier: License :: OSI Approved :: MIT License
Classifier: Operating System :: OS Independent
License-File: LICENSE
Requires-Dist: requests
Requires-Dist: matplotlib
Requires-Dist: pandas
Requires-Dist: lxml
